airtime/__init__.py
airtime/airtime.py
airtime/schema.py
data_subscription/__init__.py
data_subscription/data_subscription.py
data_subscription/schema.py
educational_payment/__init__.py
educational_payment/educational_payment.py
educational_payment/schema.py
electricity_payment/__init__.py
electricity_payment/electricity_payment.py
electricity_payment/schema.py
tv_subscriptions/__init__.py
tv_subscriptions/schema.py
tv_subscriptions/tv_subscription.py
vtpass/__init__.py
vtpass/main.py
vtpass/schema.py
vtpass/test.py
vtpass_python_sdk-0.1.1.dist-info/LICENSE
vtpass_python_sdk-0.1.1.dist-info/METADATA
vtpass_python_sdk-0.1.1.dist-info/WHEEL
vtpass_python_sdk-0.1.1.dist-info/top_level.txt
vtpass_python_sdk-0.1.1.dist-info/RECORD
