Metadata-Version: 2.1
Name: vtpass-python-sdk
Version: 0.1.1
Summary: VTPass Python SDK to interact with various services provided by VTPass. The SDK allows you to perform operations such as checking wallet balance, purchasing airtime, and subscribing to data services.
Home-page: https://github.com/Abiorh001/vtpass-pythonsdk.git
Author: Abiola Adeshina
Author-email: abiolaadedayo1993@gmail.com
License: UNKNOWN
Platform: UNKNOWN
Classifier: Programming Language :: Python :: 3
Classifier: License :: OSI Approved :: MIT License
Classifier: Operating System :: OS Independent
License-File: LICENSE
Requires-Dist: annotated-types ==0.7.0
Requires-Dist: certifi ==2024.6.2
Requires-Dist: charset-normalizer ==3.3.2
Requires-Dist: idna ==3.7
Requires-Dist: pydantic-core ==2.18.4
Requires-Dist: pydantic ==2.7.4
Requires-Dist: python-decouple ==3.8
Requires-Dist: python-dotenv ==1.0.1
Requires-Dist: pytz ==2024.1
Requires-Dist: requests ==2.32.3
Requires-Dist: typing-extensions ==4.12.2
Requires-Dist: urllib3 ==2.2.1
